ms365sync/__init__.py
ms365sync/cli.py
ms365sync/sharepoint_sync.py
ms365sync/utils.py
ms365sync-0.3.4.dist-info/METADATA
ms365sync-0.3.4.dist-info/WHEEL
ms365sync-0.3.4.dist-info/entry_points.txt
ms365sync-0.3.4.dist-info/top_level.txt
ms365sync-0.3.4.dist-info/RECORD
