Metadata-Version: 2.4
Name: ms365sync
Version: 0.3.4
Summary: A Python library for syncing files between Microsoft 365 SharePoint and local storage
Author-email: Abdullah Meda <aiteam@phianalytica.com>
Maintainer-email: Abdullah Meda <aiteam@phianalytica.com>
Project-URL: Homepage, https://github.com/Phi4AI/ms365sync
Project-URL: Bug Reports, https://github.com/Phi4AI/ms365sync/issues
Keywords: microsoft,office365,sharepoint,sync,graph-api
Classifier: Development Status :: 4 - Beta
Classifier: Intended Audience :: Developers
Classifier: Operating System :: OS Independent
Classifier: Programming Language :: Python :: 3
Classifier: Programming Language :: Python :: 3.8
Classifier: Programming Language :: Python :: 3.9
Classifier: Programming Language :: Python :: 3.10
Classifier: Programming Language :: Python :: 3.11
Classifier: Programming Language :: Python :: 3.12
Classifier: Topic :: Office/Business
Classifier: Topic :: Internet :: WWW/HTTP
Classifier: Topic :: Software Development :: Libraries :: Python Modules
Requires-Python: >=3.8
Requires-Dist: msal>=1.20.0
Requires-Dist: requests>=2.28.0
Requires-Dist: python-dotenv>=0.19.0
Provides-Extra: dev
Requires-Dist: pytest; extra == "dev"
Requires-Dist: pytest-cov; extra == "dev"
Requires-Dist: ruff; extra == "dev"
Requires-Dist: mypy; extra == "dev"
Requires-Dist: pre-commit; extra == "dev"
